ppi_origami/__init__.py
ppi_origami/__main__.py
ppi_origami/analysis.py
ppi_origami/sources/__init__.py
ppi_origami/sources/biogrid.py
ppi_origami/sources/common.py
ppi_origami/sources/deepppi.py
ppi_origami/sources/dscript.py
ppi_origami/sources/hippie.py
ppi_origami/sources/intrepppid.py
ppi_origami/sources/irefweb.py
ppi_origami/sources/oma.py
ppi_origami/sources/pipr.py
ppi_origami/sources/rapppid.py
ppi_origami/sources/string.py
ppi_origami/sources/uniprot.py
ppi_origami/sources/uniref.py
ppi_origami/sources/utils.py
ppi_origami-0.1.4.dist-info/LICENSE.md
ppi_origami-0.1.4.dist-info/METADATA
ppi_origami-0.1.4.dist-info/WHEEL
ppi_origami-0.1.4.dist-info/entry_points.txt
ppi_origami-0.1.4.dist-info/RECORD
